aiogramarch/__init__.py
aiogramarch/app.py
aiogramarch/config.py
aiogramarch/context.py
aiogramarch/generator.py
aiogramarch/templates/__init__.py
aiogramarch/templates/apps/app/__init__.py
aiogramarch/templates/apps/app/cookiecutter.json
aiogramarch/templates/apps/app/{{ cookiecutter.app_name }}/__init__.py
aiogramarch/templates/apps/app/{{ cookiecutter.app_name }}/callback_factory.py
aiogramarch/templates/apps/app/{{ cookiecutter.app_name }}/handlers.py
aiogramarch/templates/apps/app/{{ cookiecutter.app_name }}/models.py
aiogramarch/templates/apps/app/{{ cookiecutter.app_name }}/services.py
aiogramarch/templates/apps/app/{{ cookiecutter.app_name }}/states.py
aiogramarch/templates/core/admin/__init__.py
aiogramarch/templates/core/admin/core.py
aiogramarch/templates/core/admin/enums.py
aiogramarch/templates/core/admin/models.py
aiogramarch/templates/core/admin/providers.py
aiogramarch/templates/core/admin/resources.py
aiogramarch/templates/core/admin/routes.py
aiogramarch/templates/core/admin/templates/base.html
aiogramarch/templates/core/admin/templates/dashboard.html
aiogramarch/templates/core/admin/templates/password.html
aiogramarch/templates/core/admin/templates/providers/login/password.html
aiogramarch/templates/core/contrib/payments/freekassa/schemas.py
aiogramarch/templates/core/contrib/payments/freekassa/services.py
aiogramarch/templates/core/contrib/user/filters.py
aiogramarch/templates/core/contrib/user/mixins.py
aiogramarch/templates/core/contrib/user/models.py
aiogramarch/templates/project/__init__.py
aiogramarch/templates/project/cookiecutter.json
aiogramarch/templates/project/{{ cookiecutter.project_name }}/env.env
aiogramarch/templates/project/{{ cookiecutter.project_name }}/main.py
aiogramarch/templates/project/{{ cookiecutter.project_name }}/pyproject.toml
aiogramarch/templates/project/{{ cookiecutter.project_name }}/readme.md
aiogramarch/templates/project/{{ cookiecutter.project_name }}/requirements.txt
aiogramarch-1.2.dist-info/entry_points.txt
aiogramarch-1.2.dist-info/LICENSE.md
aiogramarch-1.2.dist-info/METADATA
aiogramarch-1.2.dist-info/WHEEL
aiogramarch-1.2.dist-info/RECORD
